{
    "default_pipelines_by_mode": {
        "STANDARD": ["xds", "xia2", "autoproc", "dozor"],
        "VECTOR": ["xds", "xia2", "autoproc", "dozor"],
        "SINGLE": ["xds", "xia2", "autoproc", "dozor"],
        "SITE": ["xds", "xia2", "autoproc", "dozor"],
        "RASTER": ["nxds", "dozor"],
        "STRATEGY": ["xds_strategy", "mosflm_strategy", "dozor"]
    },
    "enable_legacy_pipelines": false,
    "only_run_legacy_strategy": false,
    "minimum_frames_for_pipelines": 5,
    "run_for_each_series_upon_run_completion": true,
    "spotfinder": {
        "peak_finding_min_resolution_A": 20.0,
        "peak_finding_max_resolution_A": 2.0,
        "peak_finding_num_peaks": 200,
        "peak_finding_min_distance": 7,
        "peak_finding_min_intensity": 10,
        "peak_finding_median_filter_size": null,
        "peak_finding_zscore_cutoff": 3.0
    },
    "xds": {
        "nproc": 32,
        "njobs": 4,
        "anomalous": true
    },
    "nxds": {
        "nproc": 16,
        "njobs": 4,
        "auto_merge": false
    },
    "xia2": {
        "pipeline": "xia2_dials",
        "nproc": 32,
        "njobs": 1,
        "fast": false,
        "trust_beam_centre": true
    },
    "xia2_ssx": {
        "nproc": 16,
        "njobs": 2
    },
    "autoproc": {
        "nproc": 16,
        "njobs": 4,
        "fast": true
    },
    "crystfel": {
        "nproc": 32,
        "peak_method": "peakfinder8",
        "min_snr": 4.5,
        "min_snr_biggest_pix": 3.5,
        "min_snr_peak_pix": 2.0,
        "min_sig": 6.0,
        "local_bg_radius": 3,
        "pdb_file": null,
        "refl_min_resolution_A": 20.0,
        "refl_max_resolution_A": 2.0,
        "min_peaks": 15,
        "no_non_hits": true,
        "indexing_methods": "xgandalf",
        "xgandalf_fast": true,
        "no_refine": false,
        "no_check_peaks": false,
        "peakfinder8_fast": true,
        "asdf_fast": true,
        "no_retry": true,
        "no_multi": true,
        "push_res": 0.0,
        "integration_mode": "Standard",
        "extra_options": "",
        "peakfinder8_threshold": 20.0,
        "peakfinder8_auto_threshold": true,
        "peakfinder8_min_pix_count": 2,
        "peakfinder8_max_pix_count": 200
    },
    "alcf_processing": {
        "enabled": false,
        "pipelines": ["xia2_ssx"],
        "mode": "per_dataset",
        "nproc": 64,
        "nodes": 1,
        "walltime": "02:00:00",
        "queue": "preemptable",
        "auto_cleanup": true
    },
    "raster_3d": {
        "enabled": false,
        "analysis_source": "dozor",
        "metric": null,
        "shift": 0.0,
        "max_peaks": 10,
        "min_size": 3,
        "percentile_threshold": 95.0,
        "step_size_um": 10.0,
        "tracker_ttl_seconds": 3600,
        "wait_timeout_s": 600,
        "retry_timeout_s": 300,
        "poll_interval_s": 15,
        "max_retries": 1,
        "min_coverage_pct": 80
    },
    "dozor": {
        "batch_size": 5,
        "beamstop_size": 100,
        "spot_size": 3,
        "spot_level": 6,
        "dist_cutoff": 20.0,
        "res_cutoff_low": 20.0,
        "res_cutoff_high": 2.5,
        "check_ice_rings": "T",
        "exclude_resolution_ranges": [],
        "min_spot_range_low": 15.0,
        "min_spot_range_high": 4.0,
        "min_spot_count": 2
    }
}